apiarm/__init__.py
apiarm/cli.py
apiarm/core/__init__.py
apiarm/core/ai.py
apiarm/core/analyzer.py
apiarm/core/arm.py
apiarm/core/cache.py
apiarm/core/config.py
apiarm/core/logger.py
apiarm/core/requester.py
apiarm/core/security.py
apiarm/models/__init__.py
apiarm/models/endpoint.py
apiarm/models/response.py
apiarm/utils/__init__.py
apiarm/utils/helpers.py
apiarm-0.1.1.dist-info/METADATA
apiarm-0.1.1.dist-info/WHEEL
apiarm-0.1.1.dist-info/entry_points.txt
apiarm-0.1.1.dist-info/top_level.txt
apiarm-0.1.1.dist-info/RECORD
