Metadata-Version: 2.4
Name: apiarm
Version: 0.1.1
Summary: API-ARM: Application Programming Interface with Automated Request Manipulator
Author-email: Rayen Bahroun <rayenbahroun999@gmail.com>
License: MIT
Project-URL: Homepage, https://bahroun.me
Project-URL: Repository, https://github.com/yourusername/apiarm
Keywords: api,http,requests,automation,security
Classifier: Development Status :: 3 - Alpha
Classifier: Intended Audience :: Developers
Classifier: License :: OSI Approved :: MIT License
Classifier: Programming Language :: Python :: 3
Classifier: Programming Language :: Python :: 3.10
Classifier: Programming Language :: Python :: 3.11
Classifier: Programming Language :: Python :: 3.12
Classifier: Topic :: Internet :: WWW/HTTP
Classifier: Topic :: Software Development :: Libraries :: Python Modules
Requires-Python: >=3.10
Requires-Dist: httpx>=0.25.0
Requires-Dist: aiohttp>=3.9.0
Requires-Dist: pydantic>=2.5.0
Requires-Dist: cryptography>=41.0.0
Requires-Dist: python-jose>=3.3.0
Requires-Dist: python-dotenv>=1.0.0
Requires-Dist: rich>=13.7.0
Requires-Dist: typer>=0.9.0
Provides-Extra: dev
Requires-Dist: pytest>=7.4.0; extra == "dev"
Requires-Dist: pytest-asyncio>=0.21.0; extra == "dev"
Requires-Dist: pytest-cov>=4.1.0; extra == "dev"
Requires-Dist: black>=23.12.0; extra == "dev"
Requires-Dist: isort>=5.13.0; extra == "dev"
Requires-Dist: mypy>=1.8.0; extra == "dev"
